sarcastic_color_scheme/__init__.py
sarcastic_color_scheme/basic_rng.py
sarcastic_color_scheme/get_random_style.py
sarcastic_color_scheme/randomize_style.py
sarcastic_color_scheme-0.2.0.dist-info/LICENSE
sarcastic_color_scheme-0.2.0.dist-info/METADATA
sarcastic_color_scheme-0.2.0.dist-info/WHEEL
sarcastic_color_scheme-0.2.0.dist-info/top_level.txt
sarcastic_color_scheme-0.2.0.dist-info/RECORD
