Metadata-Version: 2.1
Name: sarcastic-color-scheme
Version: 0.2.0
Summary: A sarcastic color scheme for matplotlib.
Home-page: https://github.com/kavigupta/sarcastic-color-scheme
Author: Kavi Gupta
Author-email: sarcastic@kavigupta.org
License: UNKNOWN
Platform: UNKNOWN
Classifier: Programming Language :: Python :: 3.5
Classifier: Programming Language :: Python :: 3.6
Classifier: Programming Language :: Python :: 3.7
Classifier: Programming Language :: Python :: 3.8
Classifier: Operating System :: OS Independent
Requires-Python: >=3.5
Requires-Dist: matplotlib
